MANIFEST.in
README.md
UNLICENSE
flask_rqify.py
setup.py
Flask_Heroku_RQify.egg-info/PKG-INFO
Flask_Heroku_RQify.egg-info/SOURCES.txt
Flask_Heroku_RQify.egg-info/dependency_links.txt
Flask_Heroku_RQify.egg-info/not-zip-safe
Flask_Heroku_RQify.egg-info/requires.txt
Flask_Heroku_RQify.egg-info/top_level.txt
assets/worker-sketch.jpg