Metadata-Version: 1.0
Name: Flask-Heroku-RQify
Version: 0.2
Summary: Automatic RQ configuration for your Heroku Flask applications.
Home-page: https://github.com/rdegges/flask-heroku-cacheify
Author: Randall Degges
Author-email: rdegges@gmail.com
License: UNLICENSE
Keywords: flask heroku cloud cache memcache memcached redis awesome
Platform: UNKNOWN
